xymap/__init__.py
xymap/_xymap.py
xymap-0.0.10.dist-info/LICENSE
xymap-0.0.10.dist-info/METADATA
xymap-0.0.10.dist-info/WHEEL
xymap-0.0.10.dist-info/top_level.txt
xymap-0.0.10.dist-info/RECORD
