Metadata-Version: 2.1
Name: xymap
Version: 0.0.10
Home-page: https://github.com/leeyang1991/xymap
Author: Yang Li
Author-email: leeyang1991@gmail.com
Requires-Python: >=3
License-File: LICENSE
Requires-Dist: xycmap
Requires-Dist: numpy
Requires-Dist: gdal
Requires-Dist: tqdm
Requires-Dist: pandas
Requires-Dist: scipy
